quacktools/__init__.py
quacktools/main.py
quacktools/app/__init__.py
quacktools/app/app.py
quacktools/cache/__init__.py
quacktools/cache/cache.py
quacktools/compiler/__init__.py
quacktools/compiler/c_compiler.py
quacktools/compiler/c_sharp_compiler.py
quacktools/compiler/compiler.py
quacktools/compiler/cpp_compiler.py
quacktools/compiler/java_compiler.py
quacktools/compiler/python_compiler.py
quacktools/constants/__init__.py
quacktools/constants/argument_constants.py
quacktools/constants/exception_constants.py
quacktools/constants/extension_constants.py
quacktools/constants/table_constants.py
quacktools/exceptions/__init__.py
quacktools/exceptions/argument_flags_not_valid_error.py
quacktools/exceptions/custom_exception.py
quacktools/exceptions/extension_not_valid_error.py
quacktools/exceptions/missing_argument_error.py
quacktools/exceptions/missing_difficulty_error.py
quacktools/exceptions/missing_test_file_error.py
quacktools/exceptions/url_not_valid_error.py
quacktools/utilities/__init__.py
quacktools/utilities/logger.py
quacktools/utilities/utility.py
quacktools-1.0.0.dist-info/LICENSE
quacktools-1.0.0.dist-info/METADATA
quacktools-1.0.0.dist-info/WHEEL
quacktools-1.0.0.dist-info/entry_points.txt
quacktools-1.0.0.dist-info/top_level.txt
quacktools-1.0.0.dist-info/RECORD
