Metadata-Version: 2.1
Name: quacktools
Version: 1.0.0
Summary: quacktools streamlines the code testing and code submission process.
Author-email: Gallon Zhou <gallonzhou04@gmail.com>
License: MIT License
Classifier: Programming Language :: Python :: 3
Classifier: License :: OSI Approved :: MIT License
Classifier: Operating System :: OS Independent
Requires-Python: >=3.7
License-File: LICENSE
